{"cameraMode":{"drawMode":0,"name":"Shaded","section":"Shading Mode"},"sceneLighting":true,"audioPlay":false,"sceneViewState":{"showFog":true,"showMaterialUpdate":false,"showSkybox":true,"showFlares":true,"showImageEffects":true,"showParticleSystems":true},"in2DMode":false,"pivot":{"x":-0.11619959771633148,"y":1.7125579118728638,"z":-0.5406350493431091},"rotation":{"x":0.1224200576543808,"y":0.2516587972640991,"z":-0.032106369733810428,"w":0.9595052599906921},"size":0.2135186791419983,"orthographic":false}